cisco_ai_mcp_scanner-4.0.3.dist-info/licenses/LICENSE
mcpscanner/__init__.py
mcpscanner/cli.py
mcpscanner/server.py
mcpscanner/api/__init__.py
mcpscanner/api/api.py
mcpscanner/api/router.py
mcpscanner/config/__init__.py
mcpscanner/config/config.py
mcpscanner/config/config_parser.py
mcpscanner/config/constants.py
mcpscanner/core/__init__.py
mcpscanner/core/auth.py
mcpscanner/core/exceptions.py
mcpscanner/core/mcp_models.py
mcpscanner/core/models.py
mcpscanner/core/report_generator.py
mcpscanner/core/result.py
mcpscanner/core/scanner.py
mcpscanner/core/analyzers/__init__.py
mcpscanner/core/analyzers/api_analyzer.py
mcpscanner/core/analyzers/base.py
mcpscanner/core/analyzers/llm_analyzer.py
mcpscanner/core/analyzers/yara_analyzer.py
mcpscanner/core/analyzers/behavioral/__init__.py
mcpscanner/core/analyzers/behavioral/code_analyzer.py
mcpscanner/core/analyzers/behavioral/alignment/__init__.py
mcpscanner/core/analyzers/behavioral/alignment/alignment_llm_client.py
mcpscanner/core/analyzers/behavioral/alignment/alignment_orchestrator.py
mcpscanner/core/analyzers/behavioral/alignment/alignment_prompt_builder.py
mcpscanner/core/analyzers/behavioral/alignment/alignment_response_validator.py
mcpscanner/core/analyzers/behavioral/alignment/threat_vulnerability_classifier.py
mcpscanner/core/static_analysis/__init__.py
mcpscanner/core/static_analysis/context_extractor.py
mcpscanner/core/static_analysis/cfg/__init__.py
mcpscanner/core/static_analysis/cfg/builder.py
mcpscanner/core/static_analysis/dataflow/__init__.py
mcpscanner/core/static_analysis/dataflow/available_expressions.py
mcpscanner/core/static_analysis/dataflow/constant_propagation.py
mcpscanner/core/static_analysis/dataflow/forward_analysis.py
mcpscanner/core/static_analysis/dataflow/liveness_analysis.py
mcpscanner/core/static_analysis/dataflow/reaching_definitions.py
mcpscanner/core/static_analysis/interprocedural/__init__.py
mcpscanner/core/static_analysis/interprocedural/call_graph_analyzer.py
mcpscanner/core/static_analysis/interprocedural/cross_file_analyzer.py
cisco_ai_mcp_scanner-4.0.3.dist-info/METADATA
cisco_ai_mcp_scanner-4.0.3.dist-info/WHEEL
cisco_ai_mcp_scanner-4.0.3.dist-info/entry_points.txt
cisco_ai_mcp_scanner-4.0.3.dist-info/top_level.txt
cisco_ai_mcp_scanner-4.0.3.dist-info/RECORD
