Metadata-Version: 2.4
Name: cisco-ai-mcp-scanner
Version: 4.0.3
Summary: A tool to scan MCP servers and tools for security findings
Author: Cisco
Classifier: Programming Language :: Python :: 3.11
Classifier: Programming Language :: Python :: 3.12
Classifier: Programming Language :: Python :: 3.13
Classifier: Operating System :: OS Independent
Classifier: Intended Audience :: Developers
Requires-Python: >=3.11
License-File: LICENSE
Requires-Dist: mcp[cli]>=1.25.0
Requires-Dist: httpx>=0.28.1
Requires-Dist: yara-python>=4.5.4
Requires-Dist: fastapi>=0.125.0
Requires-Dist: uvicorn>=0.29.0
Requires-Dist: pydantic>=2.6.0
Requires-Dist: python-dotenv>=1.0.0
Requires-Dist: litellm>=1.77.0
Requires-Dist: expandvars>=0.12.0
Dynamic: license-file
